{"name":"Stockmart","tagline":"A java based multiplayer Virtual Stock Exchange Game (VSE)","body":"StockMart\r\n=========\r\n\r\nA java based Virtual Stock Exchange Game (VSE)\r\n\r\n<h2>Description:</h2>\r\nI developed the application in two parts, a client applet which interacts with a server application via TCP. The features of the client applet include live ranking, chat discussion, news items, company stocks and their market values, the status of share market and sensex. The features of the admin application (server) include live view of the users, their details, stocks and money, set news items, set time limit, block chat, delete user, view rankings, chat discussion and edit stock prices.\r\n\r\n<h2>Features and Improvements (Branch: real-bid):</h2>\r\nIntroduced real bidding whereas the code in the master branch operates on Monte Carlo simulation and there is no real bidding. Introduced many new features like bid graphs and order queue graphs !!! Fixed many bugs.... Developed a matching engine for matching orders or bids..... Improved code structure....\r\n\r\n<h2>Screenshots:</h2>\r\n<h3>Server:</h3>\r\n<div style=\"width: 200px;\">\r\n<img src=\"https://cloud.githubusercontent.com/assets/4680789/6779388/8e467fd6-d181-11e4-8856-6c0bba4545bd.PNG\">\r\n<img src=\"https://cloud.githubusercontent.com/assets/4680789/6779390/8e522958-d181-11e4-8c97-6917a0f89271.PNG\">\r\n<img src=\"https://cloud.githubusercontent.com/assets/4680789/6779391/8e5e2668-d181-11e4-907f-83e38c6a4124.PNG\">\r\n<img src=\"https://cloud.githubusercontent.com/assets/4680789/6779395/8ee84fb4-d181-11e4-865f-4e23871e0c8a.PNG\">\r\n</div>\r\n<h3>Client:</h3>\r\n<div style=\"width: 200px;\">\r\n<img src=\"https://cloud.githubusercontent.com/assets/4680789/6779389/8e4ead82-d181-11e4-8c69-0cae8d9bfd46.PNG\">\r\n<img src=\"https://cloud.githubusercontent.com/assets/4680789/6779396/8efc74bc-d181-11e4-99ab-0274500ed4e8.PNG\">\r\n</div>","google":"UA-61113017-1","note":"Don't delete this file! It's used internally to help with page regeneration."}